LICENSE.txt
README.txt
setup.cfg
setup.py
asibsync/__init__.py
asibsync/__main__.py
asibsync/asi_agent.py
asibsync/sib_agent.py
asibsync/util.py
asibsync.egg-info/PKG-INFO
asibsync.egg-info/SOURCES.txt
asibsync.egg-info/dependency_links.txt
asibsync.egg-info/entry_points.txt
asibsync.egg-info/requires.txt
asibsync.egg-info/top_level.txt
asibsync.egg-info/zip-safe
docs/HISTORY.txt
test/__init__.py
test/sib_agent_test.py