Metadata-Version: 1.0
Name: asibsync
Version: 0.9.5
Summary: ASI-SIB synchronization agent
Home-page: http://asibsync.sourceforge.net
Author: Eemeli Kantola
Author-email: eemeli.kantola@iki.fi
License: BSD
Keywords: ASI Smart-M3 SIB sync
Platform: UNKNOWN
Classifier: Development Status :: 4 - Beta
Classifier: Intended Audience :: Developers
Classifier: Programming Language :: Python :: 2.6
Classifier: Topic :: Internet
